bsb_hdf5/__init__.py
bsb_hdf5/chunks.py
bsb_hdf5/connectivity_set.py
bsb_hdf5/file_store.py
bsb_hdf5/morphology_repository.py
bsb_hdf5/placement_set.py
bsb_hdf5/resource.py
bsb_hdf5-7.2.1.dist-info/entry_points.txt
bsb_hdf5-7.2.1.dist-info/licenses/LICENSE
bsb_hdf5-7.2.1.dist-info/WHEEL
bsb_hdf5-7.2.1.dist-info/METADATA
bsb_hdf5-7.2.1.dist-info/RECORD
